ddc_indices/__init__.py
ddc_indices/__version__.py
ddc_indices/compute.py
ddc_indices/config.py
ddc_indices/constants.py
ddc_indices/errors.py
ddc_indices/eto.py
ddc_indices/indices.py
ddc_indices/metadata.py
ddc_indices/utils.py
ddc_indices-0.5.2.dist-info/LICENSE
ddc_indices-0.5.2.dist-info/METADATA
ddc_indices-0.5.2.dist-info/WHEEL
ddc_indices-0.5.2.dist-info/top_level.txt
ddc_indices-0.5.2.dist-info/RECORD
