Metadata-Version: 2.1
Name: ddc-indices
Version: 0.5.2
Summary: Package for calculating meteorological indices
Author-email: Balint Alfoldy <balint.alfoldy@lechnerkozpont.hu>
Classifier: Programming Language :: Python :: 3
Classifier: License :: OSI Approved :: MIT License
Classifier: Operating System :: OS Independent
Requires-Python: >=3.8
License-File: LICENSE
Requires-Dist: importlib-metadata (>=6.0.0)
Requires-Dist: matplotlib (>=3.6.2)
Requires-Dist: pydantic (>=1.10.0)
Requires-Dist: scipy (>=1.9.1)
Requires-Dist: xarray (>=2023.1.0)
Requires-Dist: zarr (>=2.13.6)
Requires-Dist: dask (>=2023.1.1)
